lightspark_bitcoin_py-0.2.8.dist-info/METADATA
lightspark_bitcoin_py-0.2.8.dist-info/WHEEL
lightspark_bitcoin_py/__init__.py
lightspark_bitcoin_py/lightspark_bitcoin_py.cpython-311-darwin.so
lightspark_bitcoin_py-0.2.8.dist-info/RECORD
