Metadata-Version: 2.1
Name: lightspark-bitcoin-py
Version: 0.2.8
Classifier: Programming Language :: Rust
Classifier: Programming Language :: Python :: Implementation :: CPython
Classifier: Programming Language :: Python :: Implementation :: PyPy
Summary: Rust Bitcoin bindings to Python interpreter.
Requires-Python: >=3.8
